{ "v": "5.5.9", "fr": 29.9700012207031, "ip": 0, "op": 60.0000024438501, "w": 800, "h": 450, "nm": "lotie", "ddd": 0, "comps": [], "layers": [{ "ddd": 0, "ind": 1, "ty": 2, "nm": "rocket.ai", "cl": "ai", "refId": "image_0", "sr": 1, "ks": { "o": { "a": 0, "k": 100, "ix": 11 }, "r": { "a": 0, "k": 0, "ix": 10 }, "p": { "a": 1, "k": [{ "i": { "x": 0.833, "y": 0.833 }, "o": { "x": 0.167, "y": 0.167 }, "t": 0, "s": [-112, 202, 0], "e": [625.715, 200.498, 0], "to": [-0.1, -0.693, 0], "ti": [-0.802, 0.755, 0] }, { "i": { "x": 0.833, "y": 0.833 }, "o": { "x": 0.167, "y": 0.167 }, "t": 35, "s": [625.715, 200.498, 0], "e": [1130.251, 200.498, 0], "to": [1.392, -1.311, 0], "ti": [-22.985, -0.077, 0] }, { "t": 55.0000022401959 }], "ix": 2 }, "a": { "a": 0, "k": [112, 56, 0], "ix": 1 }, "s": { "a": 0, "k": [100, 100, 100], "ix": 6 } }, "ao": 0, "ip": 0, "op": 60.0000024438501, "st": 0, "bm": 0 }, { "ddd": 0, "ind": 2, "ty": 2, "nm": "icon.ai", "cl": "ai", "refId": "image_1", "sr": 1, "ks": { "o": { "a": 1, "k": [{ "i": { "x": [0.833], "y": [0.833] }, "o": { "x": [0.167], "y": [0.167] }, "t": 24, "s": [0], "e": [39.514] }, { "i": { "x": [0.833], "y": [0.833] }, "o": { "x": [0.167], "y": [0.167] }, "t": 32, "s": [39.514], "e": [71.986] }, { "i": { "x": [0.833], "y": [0.833] }, "o": { "x": [0.167], "y": [0.167] }, "t": 38, "s": [71.986], "e": [100] }, { "t": 44.0000017921567 }], "ix": 11 }, "r": { "a": 0, "k": 0, "ix": 10 }, "p": { "a": 0, "k": [299, 206, 0], "ix": 2 }, "a": { "a": 0, "k": [59, 64.5, 0], "ix": 1 }, "s": { "a": 0, "k": [44.068, 34.884, 100], "ix": 6 } }, "ao": 0, "ip": 0, "op": 60.0000024438501, "st": 0, "bm": 0 }, { "ddd": 0, "ind": 3, "ty": 2, "nm": "dev.ai", "cl": "ai", "refId": "image_2", "sr": 1, "ks": { "o": { "a": 1, "k": [{ "i": { "x": [0.833], "y": [0.833] }, "o": { "x": [0.167], "y": [0.167] }, "t": 26, "s": [0], "e": [39.514] }, { "i": { "x": [0.833], "y": [0.833] }, "o": { "x": [0.167], "y": [0.167] }, "t": 36, "s": [39.514], "e": [71.986] }, { "i": { "x": [0.833], "y": [0.833] }, "o": { "x": [0.167], "y": [0.167] }, "t": 45, "s": [71.986], "e": [100] }, { "t": 50.0000020365418 }], "ix": 11 }, "r": { "a": 0, "k": 0, "ix": 10 }, "p": { "a": 0, "k": [369, 204, 0], "ix": 2 }, "a": { "a": 0, "k": [78.5, 39, 0], "ix": 1 }, "s": { "a": 0, "k": [47.771, 43.59, 100], "ix": 6 } }, "ao": 0, "ip": 0, "op": 60.0000024438501, "st": 0, "bm": 0 }, { "ddd": 0, "ind": 4, "ty": 2, "nm": "lights.ai", "cl": "ai", "refId": "image_3", "sr": 1, "ks": { "o": { "a": 1, "k": [{ "i": { "x": [0.833], "y": [0.833] }, "o": { "x": [0.167], "y": [0.167] }, "t": 30, "s": [0], "e": [34.067] }, { "i": { "x": [0.833], "y": [0.833] }, "o": { "x": [0.167], "y": [0.167] }, "t": 41, "s": [34.067], "e": [62.762] }, { "i": { "x": [0.654], "y": [0.583] }, "o": { "x": [0.167], "y": [0.167] }, "t": 46, "s": [62.762], "e": [98.374] }, { "t": 51.0000020772726 }], "ix": 11 }, "r": { "a": 0, "k": 0, "ix": 10 }, "p": { "a": 0, "k": [459, 208, 0], "ix": 2 }, "a": { "a": 0, "k": [114, 52, 0], "ix": 1 }, "s": { "a": 0, "k": [44.737, 40.385, 100], "ix": 6 } }, "ao": 0, "ip": 0, "op": 60.0000024438501, "st": 0, "bm": 0 }], "markers": [{ "tm": 0, "cm": "2", "dr": 0 }, { "tm": 48.0000019550801, "cm": "1", "dr": 0 }] }